README.md
setup.py
TOPSIS_Harsh_101803327.egg-info/PKG-INFO
TOPSIS_Harsh_101803327.egg-info/SOURCES.txt
TOPSIS_Harsh_101803327.egg-info/dependency_links.txt
TOPSIS_Harsh_101803327.egg-info/entry_points.txt
TOPSIS_Harsh_101803327.egg-info/requires.txt
TOPSIS_Harsh_101803327.egg-info/top_level.txt
src/topsis.py